mento/__init__.py
mento/cli.py
mento/fonts/lora/Lora-Bold.ttf
mento/fonts/lora/Lora-BoldItalic.ttf
mento/fonts/lora/Lora-Italic.ttf
mento/fonts/lora/Lora-Regular.ttf
mento/parser.py
mento/stats.py
mento/store.py
mento/types.py
mento/ui.py
mento/util.py
mento/viz.py
mento-3.0.0.dist-info/entry_points.txt
mento-3.0.0.dist-info/WHEEL
mento-3.0.0.dist-info/METADATA
mento-3.0.0.dist-info/RECORD
