Metadata-Version: 2.1
Name: mento
Version: 3.0.0
Summary: Personal tracker for mental health
Author: Abhinav Tushar
Author-email: abhinav@lepisma.xyz
Requires-Python: >=3.8,<4.0
Classifier: Programming Language :: Python :: 3
Classifier: Programming Language :: Python :: 3.8
Classifier: Programming Language :: Python :: 3.9
Requires-Dist: PyQt5 (>=5.15.2,<6.0.0)
Requires-Dist: docopt (>=0.6.2,<0.7.0)
Requires-Dist: dominate (>=2.6.0,<3.0.0)
Requires-Dist: matplotlib (>=3.3.4,<4.0.0)
Requires-Dist: org-python (>=0.3.2,<0.4.0)
Requires-Dist: orgparse (>=0.1.4,<0.2.0)
Requires-Dist: pydash (>=4.9.0,<5.0.0)
Requires-Dist: python-gnupg (>=0.4.6,<0.5.0)
Requires-Dist: textblob (>=0.15.3,<0.16.0)
Requires-Dist: tqdm (>=4.48.2,<5.0.0)
